{
  "product_name": "Interval Sports Bra A-C",
  "color": "Coastal Teal",
  "parent_color": null,
  "full_name": "Interval Sports Bra A-C | Coastal Teal",
  "category": "Bras > All Sports Bras",
  "description": "BEST FOR CARDIO: run + train + HIIT IMPACT: Medium-impact workouts, best for A-C cups FEEL: PowerMove fabric is sleek, weightless, and helps keep you cool with quick-drying properties FAVE: Stay-put straps and shaping seams for a secure, sculpted fit Built-in pockets with removable pads for optional coverage Removable pads hold their shape from wash to wear Lined with PowerMesh for breathable, sheer-proof coverage Easily pairs with the Empower Mastectomy Bra Insert Product #413272",
  "price": 29.99,
  "currency": "USD",
  "sizes_available": 5,
  "materials": null,
  "rating": 4.72,
  "rating_count": 2711,
  "sku_style": "413272",
  "sku_color": "413272652",
  "brand": "Athleta",
  "source_url": "https://athleta.gap.com/browse/product.do?pid=413272652",
  "image_files": [
    "COASTAL_TEAL_01.jpg",
    "COASTAL_TEAL_02.jpg",
    "COASTAL_TEAL_03.jpg",
    "COASTAL_TEAL_04.jpg",
    "COASTAL_TEAL_05.jpg"
  ],
  "image_source_urls": [
    "https://athleta.gap.com/webcontent/0062/598/565/cn62598565.jpg",
    "https://athleta.gap.com/webcontent/0062/598/459/cn62598459.jpg",
    "https://athleta.gap.com/webcontent/0062/598/489/cn62598489.jpg",
    "https://athleta.gap.com/webcontent/0062/598/504/cn62598504.jpg",
    "https://athleta.gap.com/webcontent/0059/593/682/cn59593682.jpg"
  ]
}