{
  "product_name": "Interval Sports Bra A-C",
  "color": "Nocturnal",
  "parent_color": null,
  "full_name": "Interval Sports Bra A-C | Nocturnal",
  "category": "Bras > All Sports Bras",
  "description": "BEST FOR CARDIO: run + train + HIIT IMPACT: Medium-impact workouts, best for A-C cups FEEL: PowerMove fabric is sleek, weightless, and helps keep you cool with quick-drying properties FAVE: Stay-put straps and shaping seams for a secure, sculpted fit Built-in pockets with removable pads for optional coverage Removable pads hold their shape from wash to wear Lined with PowerMesh for breathable, sheer-proof coverage Easily pairs with the Empower Mastectomy Bra Insert Product #413272",
  "price": 49,
  "currency": "USD",
  "sizes_available": 5,
  "materials": null,
  "rating": 4.72,
  "rating_count": 2711,
  "sku_style": "413272",
  "sku_color": "413272692",
  "brand": "Athleta",
  "source_url": "https://athleta.gap.com/browse/product.do?pid=413272692",
  "image_files": [
    "NOCTURNAL_01.jpg",
    "NOCTURNAL_02.jpg",
    "NOCTURNAL_03.jpg",
    "NOCTURNAL_04.jpg",
    "NOCTURNAL_05.jpg"
  ],
  "image_source_urls": [
    "https://athleta.gap.com/webcontent/0062/821/638/cn62821638.jpg",
    "https://athleta.gap.com/webcontent/0062/822/760/cn62822760.jpg",
    "https://athleta.gap.com/webcontent/0062/822/726/cn62822726.jpg",
    "https://athleta.gap.com/webcontent/0063/010/874/cn63010874.jpg",
    "https://athleta.gap.com/webcontent/0059/593/682/cn59593682.jpg"
  ]
}